{
    "version": "1.0.24",
    "type": "clean",
    "assets": "http://xxx.com/dist/",
    "es6": true,
    "webp": false,
    "legolib": false,
    "https": false,
    "hot": false,
    "isUglifyJs": true,
    "isPackVueStyle": false,
    "vue@2.1": false,
    "watch": [],
    "publicPath": "",
    "packImgSize": "",
    "packCommon": "",
    "other": "",
    "dist": "",
    "output": "",
    "shell": "",
    "alias": {},
    "global": {},
    "externals": {},
    "proxy": {},
    "ts": {},
    "cache": "timestamp",
    "user.dev.args": {},
    "user.build.args": {},
    "env": {},
    "build.move": [],
    "build.env": "",
    "build.zip": "",
    "img.folder": "image",
    "html.folder": ""
}